Metadata-Version: 2.1
Name: gorillamind-scraper-test
Version: 0.0.1
Summary: A test package which scrapes the gorilla mind website
Home-page: UNKNOWN
Author: Ismael Patel
License: UNKNOWN
Platform: UNKNOWN
